EitaaAPI/__init__.py
EitaaAPI/default_vars.py
EitaaAPI/sender.py
eitaaapi-0.0.1.dist-info/METADATA
eitaaapi-0.0.1.dist-info/WHEEL
eitaaapi-0.0.1.dist-info/licenses/LICENSE
eitaaapi-0.0.1.dist-info/RECORD
