Metadata-Version: 2.4
Name: EitaaAPI
Version: 0.0.1
Summary: A small client which interacts with the EitaaYar API
Project-URL: Homepage, https://github.com/ProgrammEverything/EitaaAPI
Project-URL: Issues, https://github.com/ProgrammEverything/EitaaAPI/issues
Author: Sasan Salehi
Author-email: Sasan Salehi <sasanxcoder@gmail.com>
Maintainer-email: Sasan salehi <sasanxcoder@gmail.com>
License: MIT License
License-File: LICENSE
Keywords: EITAAAPI,Eitaa,EitaaApi,Eitaa_Api,eitaa,eitaa_api,eitaaapi
Classifier: Development Status :: 4 - Beta
Classifier: Intended Audience :: Developers
Classifier: License :: OSI Approved :: MIT License
Classifier: Operating System :: OS Independent
Classifier: Programming Language :: Python :: 3
Classifier: Topic :: Utilities
Requires-Python: >=3.8
Requires-Dist: aiohttp
Requires-Dist: requests
